[
	{
		"Title": "State of The Browser 2012",
		"Slug": "state-of-the-browser-2012",
		"Date": "28 April 2012",
		"MachineDate": "2012-04-28",
		"Keywords": "",
		"Description": "",
		"Tags": [
			"html5"
		]
	},
	{
		"Title": "Goodbye Posterous",
		"Slug": "goodbye-posterous",
		"Date": "23 March 2012",
		"MachineDate": "2012-03-23",
		"Keywords": "",
		"Description": "",
		"Tags": [
			
		]
	},
	{
		"Title": "Hybrid People",
		"Slug": "hybrid-people",
		"Date": "26 February 2012",
		"MachineDate": "2012-02-26",
		"Keywords": "",
		"Description": "",
		"Tags": [
			"design",
			"philosophy"
		]
	},
	{
		"Title": "Sustaining vs Disruptive Innovation",
		"Slug": "sustaining-vs-disruptive-innovation",
		"Date": "15 January 2012",
		"MachineDate": "2012-01-15",
		"Keywords": "",
		"Description": "",
		"Tags": [
			"business",
			"innovation"
		]
	},
	{
		"Title": "Live every day as if it's your first",
		"Slug": "live-every-day-as-if-its-your-first",
		"Date": "3 December 2011",
		"MachineDate": "2011-12-03",
		"Keywords": "",
		"Description": "",
		"Tags": [
			"philosophy"
		]
	},
	{
		"Title": "Treehouse Autoplay Chrome Extension",
		"Slug": "treehouse-autoplay-chrome-extension",
		"Date": "13 November 2011",
		"MachineDate": "2011-11-13",
		"Keywords": "",
		"Description": "",
		"Tags": [
			"treehouse",
			"chrome"
		]
	},
	{
		"Title": "Treehouse is here!",
		"Slug": "treehouse-is-here",
		"Date": "7 November 2011",
		"MachineDate": "2011-11-07",
		"Keywords": "",
		"Description": "",
		"Tags": [
			"treehouse"
		]
	},
	{
		"Title": "Inspirational People",
		"Slug": "inspirational-people",
		"Date": "20 August 2011",
		"MachineDate": "2011-08-20",
		"Keywords": "",
		"Description": "",
		"Tags": [
			"business",
			"entrepreneurship"
		]
	},
	{
		"Title": "Returning to the blogosphere",
		"Slug": "returning-to-the-blogosphere",
		"Date": "11 August 2011",
		"MachineDate": "2011-08-11",
		"Keywords": "",
		"Description": "",
		"Tags": [
			
		]
	},
	{
		"Title": "Onward by Howard Schultz",
		"Slug": "onward-by-howard-schultz",
		"Date": "26 June 2011",
		"MachineDate": "2011-06-26",
		"Keywords": "",
		"Description": "",
		"Tags": [
			
		]
	},
	{
		"Title": "Who knew it. I can read!",
		"Slug": "who-knew-it-i-can-read",
		"Date": "11 June 2011",
		"MachineDate": "2011-06-11",
		"Keywords": "",
		"Description": "",
		"Tags": [
			
		]
	},
	{
		"Title": "Chrome to Phone Concept",
		"Slug": "chrome-to-phone-concept",
		"Date": "1 June 2011",
		"MachineDate": "2011-06-01",
		"Keywords": "",
		"Description": "",
		"Tags": [
			
		]
	},
	{
		"Title": "Speed up browsing with Google Public DNS",
		"Slug": "speed-up-browsing-with-google-public-dns",
		"Date": "17 May 2011",
		"MachineDate": "2011-05-17",
		"Keywords": "",
		"Description": "",
		"Tags": [
			
		]
	},
	{
		"Title": "Free Range Data",
		"Slug": "free-range-data",
		"Date": "1 May 2011",
		"MachineDate": "2011-05-01",
		"Keywords": "",
		"Description": "",
		"Tags": [
			
		]
	},
	{
		"Title": "Look after your customers and they will look after you - The long term theory",
		"Slug": "look-after-your-customers-and-they-will-look",
		"Date": "30 April 2011",
		"MachineDate": "2011-04-30",
		"Keywords": "",
		"Description": "",
		"Tags": [
			
		]
	}
]